{
  "design_system": {
    "identity": {
      "name": "SignSync AI",
      "archetype": "Cyber-Humanism",
      "vibe": "Empowering, Precision, Bridge-building",
      "emotional_tone": "Electric & Neon (Future/Tech) mixed with Organic (Human Connection)"
    },
    "typography": {
      "font_family": {
        "headings": "Manrope, sans-serif",
        "body": "Inter, sans-serif",
        "mono": "JetBrains Mono, monospace"
      },
      "weights": {
        "headings": "font-bold (700) or font-extrabold (800)",
        "body": "font-normal (400)",
        "emphasis": "font-semibold (600)"
      },
      "scale": {
        "h1": "text-5xl md:text-7xl tracking-tight leading-none",
        "h2": "text-3xl md:text-5xl tracking-tight",
        "h3": "text-2xl md:text-3xl tracking-normal",
        "body_lg": "text-lg md:text-xl leading-relaxed",
        "body_sm": "text-sm leading-relaxed text-muted-foreground"
      },
      "rules": [
        "Headings must use tight tracking.",
        "Never use 'Space Grotesk'.",
        "Use JetBrains Mono for any data values, confidence scores, or translation logs."
      ]
    },
    "colors": {
      "mode": "dark",
      "palette": {
        "background": "#09090b",
        "foreground": "#fafafa",
        "primary": "#22d3ee",
        "primary_foreground": "#000000",
        "secondary": "#f472b6",
        "secondary_foreground": "#000000",
        "accent": "#facc15",
        "muted": "#27272a",
        "border": "#27272a",
        "card": "#18181b"
      },
      "gradients": {
        "hero_glow": "bg-gradient-to-tr from-cyan-500/20 via-purple-500/10 to-transparent",
        "active_border": "bg-gradient-to-r from-cyan-400 via-blue-500 to-purple-600"
      },
      "usage": {
        "primary": "Use for 'Active Recognition' states, primary CTAs, and high-confidence matches.",
        "secondary": "Use for 'Human' elements, translation history, and learning features.",
        "accent": "Use for warnings, low confidence scores, or error states.",
        "background": "Deep Zinc-950. Never pure black (#000000) unless for OLED optimization toggle."
      }
    },
    "visual_enhancers": {
      "glassmorphism": {
        "style": "Crystal Glass",
        "classes": "bg-black/40 backdrop-blur-xl border border-white/10 shadow-2xl"
      },
      "borders": {
        "default": "border border-white/5",
        "active": "border-cyan-500/50 shadow-[0_0_15px_rgba(34,211,238,0.3)]"
      },
      "shadows": {
        "glow": "shadow-[0_0_30px_-5px_rgba(34,211,238,0.3)]",
        "card": "shadow-xl shadow-black/40"
      },
      "textures": {
        "noise": "Use a subtle SVG noise overlay on the main background to prevent banding and add tactility."
      }
    },
    "layout_strategy": {
      "spacing": {
        "container_padding": "p-6 md:p-12 lg:p-24",
        "section_gap": "gap-16 md:gap-32",
        "internal_gap": "gap-6"
      },
      "grids": {
        "landing": "Mode A: Tetris Grid (Asymmetrical bento box)",
        "dashboard": "Mode B: Control Room Grid (Dense, data-heavy, webcam-centric)"
      },
      "containers": {
        "webcam_stage": "Aspect ratio 16:9 or 4:3. Must be the visual anchor. Use 'Tracing Beam' border effect when active."
      }
    },
    "components": {
      "buttons": {
        "primary": "h-12 px-8 rounded-full bg-primary text-primary-foreground font-bold hover:scale-105 transition-transform",
        "secondary": "h-12 px-8 rounded-full border border-white/10 hover:bg-white/5 transition-colors",
        "ghost": "hover:bg-white/5 text-muted-foreground hover:text-foreground"
      },
      "cards": {
        "style": "bg-card/50 backdrop-blur-md border border-white/5 rounded-2xl p-6 hover:border-white/10 transition-colors"
      },
      "inputs": {
        "style": "bg-black/20 border-white/10 focus:border-cyan-500/50 focus:ring-1 focus:ring-cyan-500/50 h-12 rounded-xl"
      }
    },
    "motion": {
      "transitions": "transition-all duration-300 ease-out",
      "micro_interactions": "Buttons scale 0.98 on click. Cards lift -2px on hover.",
      "page_load": "Staggered fade-in up for all children elements.",
      "recognition_feedback": "Instant border color change (Gray -> Cyan) when hand is detected."
    },
    "accessibility": {
      "contrast": "Ensure 4.5:1 contrast ratio for all text. Use APCA standards.",
      "focus_states": "Visible ring-2 ring-cyan-400 ring-offset-2 ring-offset-black",
      "reduced_motion": "Respect prefers-reduced-motion media query.",
      "aria": "All icons must have aria-hidden='true' or descriptive labels. Video feed must have status announcements."
    },
    "media": {
      "image_style": "High contrast, cinematic lighting, diverse representation of signers.",
      "video_style": "Clean feed, no filters, high frame rate priority."
    },
    "3d_libraries": {
      "hero_element": {
        "library": "Spline or React Three Fiber",
        "concept": "Abstract digital hands forming connections or nodes.",
        "fallback": "High-quality 3D render image of a cybernetic hand."
      }
    }
  },
  "image_urls": {
    "hero_background": {
      "url": "https://images.unsplash.com/photo-1733370446176-cf060c668a28?crop=entropy&cs=srgb&fm=jpg&q=85",
      "description": "Man with hands on chest, emotional connection, dark background. Use with heavy overlay/gradient.",
      "category": "Hero"
    },
    "feature_recognition": {
      "url": "https://images.unsplash.com/photo-1758577515333-e71b713059f1?crop=entropy&cs=srgb&fm=jpg&q=85",
      "description": "Tech focus, smart ring/circuits. Represents the AI/Tech aspect.",
      "category": "Features"
    },
    "community_section": {
      "url": "https://images.pexels.com/photos/4631064/pexels-photo-4631064.jpeg",
      "description": "Diverse group communicating. Represents the user base.",
      "category": "Social Proof"
    },
    "dictionary_placeholder": {
      "url": "https://images.pexels.com/photos/1981863/pexels-photo-1981863.jpeg",
      "description": "Generic signing hand for dictionary card backgrounds.",
      "category": "Dictionary"
    }
  },
  "instructions_to_main_agent": {
    "general": [
      "Implement the 'Cyber-Humanism' aesthetic: Dark mode, neon accents, glassmorphism.",
      "Use 'Manrope' for all headings. Do NOT use Inter for headings.",
      "Ensure the Webcam component is the visual centerpiece of the Dashboard.",
      "Use the 'Tracing Beam' effect on the webcam container to show active state.",
      "Strictly follow the 'Control Room' grid for the dashboard layout.",
      "Add 'data-testid' to ALL interactive elements."
    ],
    "specific_files": {
      "tailwind_config": "Update colors to match the 'colors' section. Add 'Manrope' to font family.",
      "index_css": "Add the noise texture overlay to the body background.",
      "components": "Customize Shadcn components to remove the default 'Vercel' look. Increase border radius to 'rounded-xl' or 'rounded-2xl'."
    }
  },
  "universal_guidelines": [
    "Do not use generic centered layouts.",
    "Create depth through layered design elements (z-index).",
    "Use glass-morphism effects with backdrop filters (12-24px blur).",
    "NEVER use 'transition: all'. Animate specific properties.",
    "NEVER center align the App container globally.",
    "Use 'sonner' for toasts.",
    "Export components as named exports, pages as default exports."
  ]
}